<?xml version="1.0" encoding="utf-16"?>
<XMLLanguage xmlns:xsi="http://www.w3.org/2001/XMLSchema-instance" xmlns:xsd="http://www.w3.org/2001/XMLSchema">
  <succsess>Erfolg</succsess>
  <fail>Fehlschlag</fail>
  <proxySettings>Proxy Einstellungen</proxySettings>
  <proxyUse>Proxy nutzen</proxyUse>
  <proxyHostename>Proxyserver Adresse</proxyHostename>
  <proxyPort>Port</proxyPort>
  <proxyUser>Benutzername</proxyUser>
  <proxyPassword>Passwort</proxyPassword>
  <colHeaderBoss>Boss</colHeaderBoss>
  <colHeaderDate>Datum</colHeaderDate>
  <colHeaderSize>Gröse</colHeaderSize>
  <colHeaderDataCorrected>Überprüft</colHeaderDataCorrected>
  <colHeaderDuration>Dauer</colHeaderDuration>
  <colHeaderSuccess>Erfolg</colHeaderSuccess>
  <colHeaderHpLeft>% übrig</colHeaderHpLeft>
  <colHeaderCM>CM</colHeaderCM>
  <colHeaderParsed>Parsed</colHeaderParsed>
  <colHeaderUploaded>Uploaded</colHeaderUploaded>
  <filterHeader>Filter</filterHeader>
  <filterBoss>Boss</filterBoss>
  <filterHPLeft>HP übrig</filterHPLeft>
  <filterDuration>Dauer</filterDuration>
  <filterDate>Datum</filterDate>
  <filterFrom>von</filterFrom>
  <filterTo>bis</filterTo>
  <filterSuccess>Erfolg</filterSuccess>
  <filterKill>Kill</filterKill>
  <filterWipe>Wipe</filterWipe>
  <filterToday>Heute</filterToday>
  <filterReset>Reset</filterReset>
  <detailsHeader>Details</detailsHeader>
  <detailsBoss>Boss:</detailsBoss>
  <detailsDate>Datum:</detailsDate>
  <detailsSize>Größe:</detailsSize>
  <detailsCorrected>Überprüft:</detailsCorrected>
  <detailsDuration>Dauer:</detailsDuration>
  <detailsSuccess>Erfolg:</detailsSuccess>
  <detailsHpLeft>HP übrig:</detailsHpLeft>
  <detailsCM>CM:</detailsCM>
  <detailsParsed>Parsed:</detailsParsed>
  <detailsUploaded>Hochgeladen:</detailsUploaded>
  <detailsOpenLocal>öffnen</detailsOpenLocal>
  <detailsOpenRemote>öffnen</detailsOpenRemote>
  <detailsAccName>Account</detailsAccName>
  <detailsSubGroup>SG</detailsSubGroup>
  <detailsDPS>DPS</detailsDPS>
  <actionsHeader>Aktionen</actionsHeader>
  <actionsParseLocal>Parse lokal</actionsParseLocal>
  <actionsOpenLocal>Öffne lokal</actionsOpenLocal>
  <actionsUpload>Upload</actionsUpload>
  <actionsOpenRemote>dps.report</actionsOpenRemote>
  <actionsParseAndUpload>Parse lokal und upload</actionsParseAndUpload>
  <actionsCopyLinks>Links kopieren</actionsCopyLinks>
  <actionsCopied>kopiert</actionsCopied>
  <actionsPostToDiscord>in Discord posten</actionsPostToDiscord>
  <actionsViewInExplorer>Zeige im Explorer</actionsViewInExplorer>
  <settingsHeader>Einstellungen</settingsHeader>
  <settingsAutoParse>Auto parse neue Logs</settingsAutoParse>
  <settingsAutoUpload>Auto upload neue Logs</settingsAutoUpload>
  <settingsAbout>Über</settingsAbout>
  <settingsSettings>Einstellungen ...</settingsSettings>
  <footerElements>Elemente</footerElements>
  <footerSelected>Ausgewählt</footerSelected>
  <footerShown>Angezeigt</footerShown>
  <footerProcessing>Verarbeite</footerProcessing>
  <footerParsing>Parse</footerParsing>
  <footerUploading>Uploading</footerUploading>
  <aboutTitle>Über</aboutTitle>
  <aboutProjectPage>Projektseite github.com</aboutProjectPage>
  <aboutViewLicense>Zeige Lizenz</aboutViewLicense>
  <aboutSpecialThanks>Vielen Dank an:</aboutSpecialThanks>
  <aboutBetaTesters>Beta Tester:</aboutBetaTesters>
  <aboutCopyright>Copyright:</aboutCopyright>
  <aboutView3rdParty>Zeige 3rd Party Bibliotheken, Software</aboutView3rdParty>
  <aboutForSpellCheck>für Spell Checking</aboutForSpellCheck>
  <aboutVersion>Version</aboutVersion>
  <licenseTitle>Lizenz</licenseTitle>
  <licenseFor>für</licenseFor>
  <licenseBy>von</licenseBy>
  <licensesTitle>Software dritter</licensesTitle>
  <licensesClose>Schliessen</licensesClose>
  <softwareItemProject>Project</softwareItemProject>
  <softwareItemViewLicense>zeige Lizenz</softwareItemViewLicense>
  <initTitle>First Setup</initTitle>
  <initArcPaht>Arc Logs Pfad:</initArcPaht>
  <initBrowse>Auswählen ...</initBrowse>
  <initLanguage>Sprache:</initLanguage>
  <initCancle>Abbrechen</initCancle>
  <initStart>Start</initStart>
  <initCancelSetupTitel>Abbruch bestätigen</initCancelSetupTitel>
  <initCancelSetupText>Setup wirklich abbrechen?</initCancelSetupText>
  <initInvalidPathTitel>Ungültiger Pfad</initInvalidPathTitel>
  <initInvalidPathText>Pfad "...\arcdps.cbtlogs\" is ungültig!</initInvalidPathText>
  <configTitle>Einstellungen</configTitle>
  <configGeneralTitle>Allgemein</configGeneralTitle>
  <configGeneralArcPaht>Arc Log Ordner Pfad</configGeneralArcPaht>
  <configGeneralBrowse>Auswählen</configGeneralBrowse>
  <configGeneralLanguage>Sprache</configGeneralLanguage>
  <configDpsReportTitle>dps.report</configDpsReportTitle>
  <configDpsReportToken>User Token:</configDpsReportToken>
  <configDpsReportGetToken>Token generieren:</configDpsReportGetToken>
  <configDpsReportProxy>Proxy Einstellungen...</configDpsReportProxy>
  <configCopyTitle>Links kopieren</configCopyTitle>
  <configCopyBoss>mit Bossname</configCopyBoss>
  <configCopySuccess>mit Erfolg</configCopySuccess>
  <configCopyInline>Link in gleiche Zeile wie Boss</configCopyInline>
  <configCopySpace>leere Zeile zwischen Logs</configCopySpace>
  <configCopyEmotes>mit RisingLight Discord Emotes</configCopyEmotes>
  <configDiscordTitle>Discord Webhooks</configDiscordTitle>
  <configDiscordWebHookName>Name:</configDiscordWebHookName>
  <configDiscordWebHookLink>Link:</configDiscordWebHookLink>
  <configDiscordWebHookFormat>Format:</configDiscordWebHookFormat>
  <configDiscordWebHookAvatar>Avatar URL:</configDiscordWebHookAvatar>
  <configDiscordWebHookDelete>Löschen</configDiscordWebHookDelete>
  <configDiscordCount>Anzahl</configDiscordCount>
  <configDiscordNoHooks>Keine Webhooks vorhanden

Füge einen neuen hinzu!</configDiscordNoHooks>
  <configDiscordAdd>Hinzufügen</configDiscordAdd>
  <configDiscordOnlyUploaded>Nur hochgeladene posten</configDiscordOnlyUploaded>
  <configDiscordNameAsUsername>Name als Discord Username</configDiscordNameAsUsername>
  <configEiTitle>EliteInsights</configEiTitle>
  <configEiCombatReplay>Erzeuge Combat-Replay</configEiCombatReplay>
  <configEiLightTheme>Nutze helles Thema</configEiLightTheme>
  <configDefault>Standard</configDefault>
  <configCancel>Abbrechen</configCancel>
  <configSave>Speichern</configSave>
  <configDefaultMsgTitel>Einstellungen zurücksetzen</configDefaultMsgTitel>
  <configDefaultMsgText>Standard Einstellungen wiederherstellen?
Dies wird deine aktuellen Einstellungen dauerhaft löschen!</configDefaultMsgText>
  <configDiscardMsgTitel>Änderungen verwerfen?</configDiscardMsgTitel>
  <configDiscardMsgText>Fortfahren ohne speichern?</configDiscardMsgText>
  <configRoPlusTitle>RaidOrga+</configRoPlusTitle>
  <configRoPlusUser>Benutzer</configRoPlusUser>
  <configRoPlusPwd>Passwort</configRoPlusPwd>
  <newTitle>Neuerungen in </newTitle>
  <newHeading>Update-Notes</newHeading>
  <newClose>Schliessen</newClose>
  <playerToCorrectPlayer>Spieler</playerToCorrectPlayer>
  <playerToCorrectAccount>Account</playerToCorrectAccount>
  <playerToCorrectMember>Mitglied</playerToCorrectMember>
  <playerToCorrectHelper>Helfer</playerToCorrectHelper>
  <playerToCorrectLFG>LFG</playerToCorrectLFG>
  <correctPlayer>Spieler korregieren</correctPlayer>
  <correctPlayerTitle>Spieler zuordnen</correctPlayerTitle>
  <correctPlayerDone>Ferig</correctPlayerDone>
  <miscGenericProcessing>Verarbeite</miscGenericProcessing>
  <miscNoWebhookMsgTitel>Webhooks erstellen</miscNoWebhookMsgTitel>
  <miscNoWebhookMsgText>Du hast aktuell keine WebHooks eingestellt
Gehe zu Discord Webhooks in den Einstellungen und erstelle einen neuen.</miscNoWebhookMsgText>
  <miscDiscordPostGenDuration>Dauer</miscDiscordPostGenDuration>
  <miscDiscordPostGenHpLeft>HP übrig</miscDiscordPostGenHpLeft>
  <miscDiscordPostGenGroupDPS>Gruppen DPS</miscDiscordPostGenGroupDPS>
  <miscDiscordPostGenTopDPS>Top DPS</miscDiscordPostGenTopDPS>
  <miscDiscordPostGenNoLink>kein Link</miscDiscordPostGenNoLink>
  <miscDiscordPostErrTitle>Discord-Post Fehler</miscDiscordPostErrTitle>
  <miscDiscordPostErrMsg>Es war nicht möglich über den Webhook %s zu posten.
Stelle sicher, dass
- die Adresse des Webhooks korrekt ist
- der Link des genutzten Avatars korrekt ist (wenn du einen nutzt)
- du mit dem Internet verbunden bist</miscDiscordPostErrMsg>
  <miscDetailsMultibleBosses>Verschieden</miscDetailsMultibleBosses>
  <miscRaidOrgaPlusNoAccount>Kein konto eingestellt</miscRaidOrgaPlusNoAccount>
  <miscRaidOrgaPlusLoginErr>Login fehlgeschlagen</miscRaidOrgaPlusLoginErr>
  <miscRaidOrgaPlusNoRaid>Kein Termin mit Leiter rechten</miscRaidOrgaPlusNoRaid>
</XMLLanguage>